Metadata-Version: 1.0
Name: python-finite-automation
Version: 0.0.5
Summary: Finite automation implementation
Home-page: https://github.com/tumb1er/python-finite-automation
Author: tumbler
Author-email: zimbler@gmail.com
License: Beer license
Platform: UNKNOWN
